README.md
setup.py
grandas/__init__.py
grandas/engine.py
grandas/graph_objects.py
grandas/graphframe.py
grandas.egg-info/PKG-INFO
grandas.egg-info/SOURCES.txt
grandas.egg-info/dependency_links.txt
grandas.egg-info/not-zip-safe
grandas.egg-info/top_level.txt