Metadata-Version: 2.1
Name: grandas
Version: 0.0.1
Summary: Simple and flexible graph database analysis
Home-page: http://github.com/austinbrian/grandas
Author: Brian Austin
Author-email: austin.brian+gh@gmail.com
License: BSD-3
Platform: UNKNOWN
